flake8_dac/__init__.py
flake8_dac/__main__.py
flake8_dac/formatting.py
flake8_dac-0.1.1.dist-info/METADATA
flake8_dac-0.1.1.dist-info/WHEEL
flake8_dac-0.1.1.dist-info/entry_points.txt
flake8_dac-0.1.1.dist-info/top_level.txt
flake8_dac-0.1.1.dist-info/RECORD
