Metadata-Version: 2.1
Name: flake8-dac
Version: 0.1.1
Summary: "Group and format flake8's output by the rules codes"
Home-page: https://github.com/mbroton/flake8-dac
Author: Michal Broton
Author-email: michal@broton.dev
Classifier: Programming Language :: Python :: 3
Classifier: Programming Language :: Python :: 3 :: Only
Classifier: Programming Language :: Python :: Implementation :: CPython
Classifier: Programming Language :: Python :: Implementation :: PyPy
Requires-Python: >=3.7
Requires-Dist: rich
